{
  "offers": [
    {
      "name": "Nouara Zaiter ",
      "villeD": "Alger",
      "villeA": "El-Harrach",
      "dateO": "2021-04-30",
      "id": 1
    },
    {
      "name": "Amira Benrabah",
      "villeD": "Alger",
      "villeA": "Zeralda",
      "dateO": "2021-05-09",
      "id": 2
    }
  ]

  "employees": [
    {
      "nom": "Nouara Zaiter ",
      "prenom": "Alger",
      "genre": "El-Harrach",
      "adressMail": "2021-04-30",
      "id": 1
    },
    {
      "nom": "Amira Benrabah",
      "prenom": "Alger",
      "genre": "Zeralda",
      "adressMail": "2021-05-09",
      "id": 2
    }
  ]
}
